["[{\"TaskID\":1,\"1\":\"https://uva.eu.qualtrics.com/ControlPanel/Graphic.php?IM=IM_cmPyLMx8m0ciqvU\",\"2\":\"https://uva.eu.qualtrics.com/ControlPanel/Graphic.php?IM=IM_uIAfmx7FUBzoyQN\",\"3\":\"https://uva.eu.qualtrics.com/ControlPanel/Graphic.php?IM=IM_lpczA43rNOAzPX0\",\"4\":\"https://uva.eu.qualtrics.com/ControlPanel/Graphic.php?IM=IM_cwwkkPrMwonq50W\"},{\"TaskID\":2,\"1\":\"https://uva.eu.qualtrics.com/ControlPanel/Graphic.php?IM=IM_vuP09XSfMfznSip\",\"2\":\"https://uva.eu.qualtrics.com/ControlPanel/Graphic.php?IM=IM_eLDAO1za8YKmSpk\",\"3\":\"https://uva.eu.qualtrics.com/ControlPanel/Graphic.php?IM=IM_NykAQvA8eVpdlJA\",\"4\":\"https://uva.eu.qualtrics.com/ControlPanel/Graphic.php?IM=IM_Pz26uZ6dj5jbt3c\"},{\"TaskID\":3,\"1\":\"https://uva.eu.qualtrics.com/ControlPanel/Graphic.php?IM=IM_M51rNWgqOminAZI\",\"2\":\"https://uva.eu.qualtrics.com/ControlPanel/Graphic.php?IM=IM_S4xLZvAR1gJI5pJ\",\"3\":\"https://uva.eu.qualtrics.com/ControlPanel/Graphic.php?IM=IM_jkokbFviAl3C8Xi\",\"4\":\"https://uva.eu.qualtrics.com/ControlPanel/Graphic.php?IM=IM_0rgWwwcP9SNwK4p\"},{\"TaskID\":4,\"1\":\"https://uva.eu.qualtrics.com/ControlPanel/Graphic.php?IM=IM_2eFe9elFPfxSkXL\",\"2\":\"https://uva.eu.qualtrics.com/ControlPanel/Graphic.php?IM=IM_l0JX3M0jtP3V5zk\",\"3\":\"https://uva.eu.qualtrics.com/ControlPanel/Graphic.php?IM=IM_5DYzPFEzkaavB9A\",\"4\":\"https://uva.eu.qualtrics.com/ControlPanel/Graphic.php?IM=IM_g26amkacYKTzckY\"},{\"TaskID\":5,\"1\":\"https://uva.eu.qualtrics.com/ControlPanel/Graphic.php?IM=IM_68aJKEfOvoa9Sds\",\"2\":\"https://uva.eu.qualtrics.com/ControlPanel/Graphic.php?IM=IM_FxlMIgtXb39pMvn\",\"3\":\"https://uva.eu.qualtrics.com/ControlPanel/Graphic.php?IM=IM_0QYJdapglmwcpdm\",\"4\":\"https://uva.eu.qualtrics.com/ControlPanel/Graphic.php?IM=IM_U3pqzNwjEqzCYL4\"},{\"TaskID\":6,\"1\":\"https://uva.eu.qualtrics.com/ControlPanel/Graphic.php?IM=IM_xNQqI0AhkVuEGB7\",\"2\":\"https://uva.eu.qualtrics.com/ControlPanel/Graphic.php?IM=IM_6A40wjqQiAU2kUa\",\"3\":\"https://uva.eu.qualtrics.com/ControlPanel/Graphic.php?IM=IM_tVPNoi6XurmBIdM\",\"4\":\"https://uva.eu.qualtrics.com/ControlPanel/Graphic.php?IM=IM_IxzHnF0mKwUn6AD\"},{\"TaskID\":7,\"1\":\"https://uva.eu.qualtrics.com/ControlPanel/Graphic.php?IM=IM_KpCkTNYD54YLAwG\",\"2\":\"https://uva.eu.qualtrics.com/ControlPanel/Graphic.php?IM=IM_sJMHMkvBKIdt4xg\",\"3\":\"https://uva.eu.qualtrics.com/ControlPanel/Graphic.php?IM=IM_2AyzY0tcnzMu981\",\"4\":\"https://uva.eu.qualtrics.com/ControlPanel/Graphic.php?IM=IM_cwwkkPrMwonq50W\"},{\"TaskID\":8,\"1\":\"https://uva.eu.qualtrics.com/ControlPanel/Graphic.php?IM=IM_od6aDkID5jxIi9n\",\"2\":\"https://uva.eu.qualtrics.com/ControlPanel/Graphic.php?IM=IM_85cIGpAqqmyGmd7\",\"3\":\"https://uva.eu.qualtrics.com/ControlPanel/Graphic.php?IM=IM_KpCkTNYD54YLAwG\",\"4\":\"https://uva.eu.qualtrics.com/ControlPanel/Graphic.php?IM=IM_eIe3VsagvONlClQ\"},{\"TaskID\":9,\"1\":\"https://uva.eu.qualtrics.com/ControlPanel/Graphic.php?IM=IM_RBWwkaP6WUNAXs3\",\"2\":\"https://uva.eu.qualtrics.com/ControlPanel/Graphic.php?IM=IM_xNQqI0AhkVuEGB7\",\"3\":\"https://uva.eu.qualtrics.com/ControlPanel/Graphic.php?IM=IM_HNjgwkcFRLYpZn6\",\"4\":\"https://uva.eu.qualtrics.com/ControlPanel/Graphic.php?IM=IM_azNPDXb1sHLwlao\"},{\"TaskID\":10,\"1\":\"https://uva.eu.qualtrics.com/ControlPanel/Graphic.php?IM=IM_hXdg0l1yc4N2aa3\",\"2\":\"https://uva.eu.qualtrics.com/ControlPanel/Graphic.php?IM=IM_WdMv72LJ07uliW7\",\"3\":\"https://uva.eu.qualtrics.com/ControlPanel/Graphic.php?IM=IM_xNAqgnhpAhoubLJ\",\"4\":\"https://uva.eu.qualtrics.com/ControlPanel/Graphic.php?IM=IM_e6ZDjPPiLhcqF2G\"},{\"TaskID\":11,\"1\":\"https://uva.eu.qualtrics.com/ControlPanel/Graphic.php?IM=IM_dwCK0Jng34RmNsB\",\"2\":\"https://uva.eu.qualtrics.com/ControlPanel/Graphic.php?IM=IM_x36w8ZJVMgeTBAm\",\"3\":\"https://uva.eu.qualtrics.com/ControlPanel/Graphic.php?IM=IM_haeLHSzp54wcIAA\",\"4\":\"https://uva.eu.qualtrics.com/ControlPanel/Graphic.php?IM=IM_SW7rAiuePZtPilS\"},{\"TaskID\":12,\"1\":\"https://uva.eu.qualtrics.com/ControlPanel/Graphic.php?IM=IM_FxlMIgtXb39pMvn\",\"2\":\"https://uva.eu.qualtrics.com/ControlPanel/Graphic.php?IM=IM_jaDVAn5OPmNr2eS\",\"3\":\"https://uva.eu.qualtrics.com/ControlPanel/Graphic.php?IM=IM_wEiUh8hJmPIdQ9b\",\"4\":\"https://uva.eu.qualtrics.com/ControlPanel/Graphic.php?IM=IM_jNlEHWA1Nq5ypZS\"}]"]
