[{"Field1":"https://uva.eu.qualtrics.com/ControlPanel/Graphic.php?IM=IM_zcgn7uf9dsxVpnx","Field2":"https://uva.eu.qualtrics.com/ControlPanel/Graphic.php?IM=IM_aqK6pcmxmclyOiv","Field3":"https://uva.eu.qualtrics.com/ControlPanel/Graphic.php?IM=IM_9HSwMrTde4Vx40l","Field4":"https://uva.eu.qualtrics.com/ControlPanel/Graphic.php?IM=IM_L0scRF1Macj2xrq"},{"Field1":"https://uva.eu.qualtrics.com/ControlPanel/Graphic.php?IM=IM_JWY40S6GeFVF8lK","Field2":"https://uva.eu.qualtrics.com/ControlPanel/Graphic.php?IM=IM_dwCK0Jng34RmNsB","Field3":"https://uva.eu.qualtrics.com/ControlPanel/Graphic.php?IM=IM_bNqbRcuX9T3AXnG","Field4":"https://uva.eu.qualtrics.com/ControlPanel/Graphic.php?IM=IM_0dPnlOPijYFWaWf"},{"Field1":"https://uva.eu.qualtrics.com/ControlPanel/Graphic.php?IM=IM_JWY40S6GeFVF8lK","Field2":"https://uva.eu.qualtrics.com/ControlPanel/Graphic.php?IM=IM_jaDVAn5OPmNr2eS","Field3":"https://uva.eu.qualtrics.com/ControlPanel/Graphic.php?IM=IM_aIEQ1ViyPkgDYsO","Field4":"https://uva.eu.qualtrics.com/ControlPanel/Graphic.php?IM=IM_EoVuWQUKYnIsQkr"},{"Field1":"https://uva.eu.qualtrics.com/ControlPanel/Graphic.php?IM=IM_aKWnCmgj2ieIEgx","Field2":"https://uva.eu.qualtrics.com/ControlPanel/Graphic.php?IM=IM_hXdg0l1yc4N2aa3","Field3":"https://uva.eu.qualtrics.com/ControlPanel/Graphic.php?IM=IM_LXpNemahgNRWABQ","Field4":"https://uva.eu.qualtrics.com/ControlPanel/Graphic.php?IM=IM_sJZKBWmVzqfQTxm"},{"Field1":"https://uva.eu.qualtrics.com/ControlPanel/Graphic.php?IM=IM_j0wj94ZHrFwUIkk","Field2":"https://uva.eu.qualtrics.com/ControlPanel/Graphic.php?IM=IM_hXdg0l1yc4N2aa3","Field3":"https://uva.eu.qualtrics.com/ControlPanel/Graphic.php?IM=IM_eNDyhAbx9JGAlCM","Field4":"https://uva.eu.qualtrics.com/ControlPanel/Graphic.php?IM=IM_sJZKBWmVzqfQTxm"},{"Field1":"https://uva.eu.qualtrics.com/ControlPanel/Graphic.php?IM=IM_yFawENxaMdrAzMy","Field2":"https://uva.eu.qualtrics.com/ControlPanel/Graphic.php?IM=IM_hXdg0l1yc4N2aa3","Field3":"https://uva.eu.qualtrics.com/ControlPanel/Graphic.php?IM=IM_qUjN9HErJ5fFhlL","Field4":"https://uva.eu.qualtrics.com/ControlPanel/Graphic.php?IM=IM_CkRaW0ADw4NYyJw"},{"Field1":"https://uva.eu.qualtrics.com/ControlPanel/Graphic.php?IM=IM_l0JX3M0jtP3V5zk","Field2":"https://uva.eu.qualtrics.com/ControlPanel/Graphic.php?IM=IM_RBWwkaP6WUNAXs3","Field3":"https://uva.eu.qualtrics.com/ControlPanel/Graphic.php?IM=IM_qUjN9HErJ5fFhlL","Field4":"https://uva.eu.qualtrics.com/ControlPanel/Graphic.php?IM=IM_CkRaW0ADw4NYyJw"},{"Field1":"https://uva.eu.qualtrics.com/ControlPanel/Graphic.php?IM=IM_gDflFevEsmawnE6","Field2":"https://uva.eu.qualtrics.com/ControlPanel/Graphic.php?IM=IM_AYAMNzl4XH7kA0e","Field3":"https://uva.eu.qualtrics.com/ControlPanel/Graphic.php?IM=IM_7E937mEmQU9bjMp","Field4":"https://uva.eu.qualtrics.com/ControlPanel/Graphic.php?IM=IM_jNlEHWA1Nq5ypZS"},{"Field1":"https://uva.eu.qualtrics.com/ControlPanel/Graphic.php?IM=IM_gDflFevEsmawnE6","Field2":"https://uva.eu.qualtrics.com/ControlPanel/Graphic.php?IM=IM_dJG9BrLvAbKqifI","Field3":"https://uva.eu.qualtrics.com/ControlPanel/Graphic.php?IM=IM_oUmm5YQ6DYyh4gS","Field4":"https://uva.eu.qualtrics.com/ControlPanel/Graphic.php?IM=IM_NykAQvA8eVpdlJA"},{"Field1":"https://uva.eu.qualtrics.com/ControlPanel/Graphic.php?IM=IM_O6lsHCxXYHUpydr","Field2":"https://uva.eu.qualtrics.com/ControlPanel/Graphic.php?IM=IM_SastNG35IifNB3i","Field3":"https://uva.eu.qualtrics.com/ControlPanel/Graphic.php?IM=IM_cwwkkPrMwonq50W","Field4":"https://uva.eu.qualtrics.com/ControlPanel/Graphic.php?IM=IM_e6ZDjPPiLhcqF2G"},{"Field1":"https://uva.eu.qualtrics.com/ControlPanel/Graphic.php?IM=IM_WFhuAj84wP2KxRE","Field2":"https://uva.eu.qualtrics.com/ControlPanel/Graphic.php?IM=IM_5FacaSuaY7PZpuh","Field3":"https://uva.eu.qualtrics.com/ControlPanel/Graphic.php?IM=IM_2AyzY0tcnzMu981","Field4":"https://uva.eu.qualtrics.com/ControlPanel/Graphic.php?IM=IM_GkspAb2S0u2jHvi"},{"Field1":"https://uva.eu.qualtrics.com/ControlPanel/Graphic.php?IM=IM_WFhuAj84wP2KxRE","Field2":"https://uva.eu.qualtrics.com/ControlPanel/Graphic.php?IM=IM_LYQUZalPb64vK8J","Field3":"https://uva.eu.qualtrics.com/ControlPanel/Graphic.php?IM=IM_uAlvAxrrxtUsAax","Field4":"https://uva.eu.qualtrics.com/ControlPanel/Graphic.php?IM=IM_vnFqzJOEaash1ao"}]
