["[{\"TaskID\":1,\"1\":\"https://uva.eu.qualtrics.com/ControlPanel/Graphic.php?IM=IM_nmjZUftOPawj0VR\",\"2\":\"https://uva.eu.qualtrics.com/ControlPanel/Graphic.php?IM=IM_XPnIKFngpJyyXrJ\",\"3\":\"https://uva.eu.qualtrics.com/ControlPanel/Graphic.php?IM=IM_aKWnCmgj2ieIEgx\",\"4\":\"https://uva.eu.qualtrics.com/ControlPanel/Graphic.php?IM=IM_SW7rAiuePZtPilS\"},{\"TaskID\":2,\"1\":\"https://uva.eu.qualtrics.com/ControlPanel/Graphic.php?IM=IM_CnEqxLAO4LAcNa3\",\"2\":\"https://uva.eu.qualtrics.com/ControlPanel/Graphic.php?IM=IM_CkRaW0ADw4NYyJw\",\"3\":\"https://uva.eu.qualtrics.com/ControlPanel/Graphic.php?IM=IM_VGGLavMckaLaioA\",\"4\":\"https://uva.eu.qualtrics.com/ControlPanel/Graphic.php?IM=IM_JCcubloQaiSKoeb\"},{\"TaskID\":3,\"1\":\"https://uva.eu.qualtrics.com/ControlPanel/Graphic.php?IM=IM_oXxe4vNb2qAR2yF\",\"2\":\"https://uva.eu.qualtrics.com/ControlPanel/Graphic.php?IM=IM_7O1hRmX8g4iVVLr\",\"3\":\"https://uva.eu.qualtrics.com/ControlPanel/Graphic.php?IM=IM_x36w8ZJVMgeTBAm\",\"4\":\"https://uva.eu.qualtrics.com/ControlPanel/Graphic.php?IM=IM_VGGLavMckaLaioA\"},{\"TaskID\":4,\"1\":\"https://uva.eu.qualtrics.com/ControlPanel/Graphic.php?IM=IM_a2p85HKN5ASGehh\",\"2\":\"https://uva.eu.qualtrics.com/ControlPanel/Graphic.php?IM=IM_wPxFDVIp234cJAM\",\"3\":\"https://uva.eu.qualtrics.com/ControlPanel/Graphic.php?IM=IM_S4xLZvAR1gJI5pJ\",\"4\":\"https://uva.eu.qualtrics.com/ControlPanel/Graphic.php?IM=IM_e6ZDjPPiLhcqF2G\"},{\"TaskID\":5,\"1\":\"https://uva.eu.qualtrics.com/ControlPanel/Graphic.php?IM=IM_4x3eDJu7MCGNDKh\",\"2\":\"https://uva.eu.qualtrics.com/ControlPanel/Graphic.php?IM=IM_LYQUZalPb64vK8J\",\"3\":\"https://uva.eu.qualtrics.com/ControlPanel/Graphic.php?IM=IM_XEWWL4tmSLtFALd\",\"4\":\"https://uva.eu.qualtrics.com/ControlPanel/Graphic.php?IM=IM_hYC2Ao940dFp5lG\"},{\"TaskID\":6,\"1\":\"https://uva.eu.qualtrics.com/ControlPanel/Graphic.php?IM=IM_O4gtcBY7fQAfSKb\",\"2\":\"https://uva.eu.qualtrics.com/ControlPanel/Graphic.php?IM=IM_XPnIKFngpJyyXrJ\",\"3\":\"https://uva.eu.qualtrics.com/ControlPanel/Graphic.php?IM=IM_Rih8NvGKD0G7mPO\",\"4\":\"https://uva.eu.qualtrics.com/ControlPanel/Graphic.php?IM=IM_oCDqBD2dOOLPQcX\"},{\"TaskID\":7,\"1\":\"https://uva.eu.qualtrics.com/ControlPanel/Graphic.php?IM=IM_0q5cc14gapxLAY2\",\"2\":\"https://uva.eu.qualtrics.com/ControlPanel/Graphic.php?IM=IM_RYlmHRoU0sIYBCg\",\"3\":\"https://uva.eu.qualtrics.com/ControlPanel/Graphic.php?IM=IM_XEWWL4tmSLtFALd\",\"4\":\"https://uva.eu.qualtrics.com/ControlPanel/Graphic.php?IM=IM_T1o28yS35YlIAEF\"},{\"TaskID\":8,\"1\":\"https://uva.eu.qualtrics.com/ControlPanel/Graphic.php?IM=IM_M51rNWgqOminAZI\",\"2\":\"https://uva.eu.qualtrics.com/ControlPanel/Graphic.php?IM=IM_LGoadVyHRXYaPnN\",\"3\":\"https://uva.eu.qualtrics.com/ControlPanel/Graphic.php?IM=IM_CnEqxLAO4LAcNa3\",\"4\":\"https://uva.eu.qualtrics.com/ControlPanel/Graphic.php?IM=IM_uAlvAxrrxtUsAax\"},{\"TaskID\":9,\"1\":\"https://uva.eu.qualtrics.com/ControlPanel/Graphic.php?IM=IM_2BrxQ9dXdkIMYWG\",\"2\":\"https://uva.eu.qualtrics.com/ControlPanel/Graphic.php?IM=IM_hZJmVuLwyjfpXFa\",\"3\":\"https://uva.eu.qualtrics.com/ControlPanel/Graphic.php?IM=IM_qDQR2dDEr2C6Gd4\",\"4\":\"https://uva.eu.qualtrics.com/ControlPanel/Graphic.php?IM=IM_FI2LebbNI48nPRU\"},{\"TaskID\":10,\"1\":\"https://uva.eu.qualtrics.com/ControlPanel/Graphic.php?IM=IM_wEiUh8hJmPIdQ9b\",\"2\":\"https://uva.eu.qualtrics.com/ControlPanel/Graphic.php?IM=IM_jaDVAn5OPmNr2eS\",\"3\":\"https://uva.eu.qualtrics.com/ControlPanel/Graphic.php?IM=IM_EEFaiNxQSaC6x3h\",\"4\":\"https://uva.eu.qualtrics.com/ControlPanel/Graphic.php?IM=IM_SW7rAiuePZtPilS\"},{\"TaskID\":11,\"1\":\"https://uva.eu.qualtrics.com/ControlPanel/Graphic.php?IM=IM_wPxFDVIp234cJAM\",\"2\":\"https://uva.eu.qualtrics.com/ControlPanel/Graphic.php?IM=IM_5FacaSuaY7PZpuh\",\"3\":\"https://uva.eu.qualtrics.com/ControlPanel/Graphic.php?IM=IM_QWE2ldL6J1QVH6t\",\"4\":\"https://uva.eu.qualtrics.com/ControlPanel/Graphic.php?IM=IM_FqG8DyUWa1kOKVA\"},{\"TaskID\":12,\"1\":\"https://uva.eu.qualtrics.com/ControlPanel/Graphic.php?IM=IM_DZrdNEkYaeu0OT5\",\"2\":\"https://uva.eu.qualtrics.com/ControlPanel/Graphic.php?IM=IM_2eFe9elFPfxSkXL\",\"3\":\"https://uva.eu.qualtrics.com/ControlPanel/Graphic.php?IM=IM_pszmuErmiIVMD4c\",\"4\":\"https://uva.eu.qualtrics.com/ControlPanel/Graphic.php?IM=IM_2C2FyNt2qJelqrt\"}]"]
